gctools/__init__.py
gctools/gctools.py
gctools-0.0.3.dist-info/METADATA
gctools-0.0.3.dist-info/WHEEL
gctools-0.0.3.dist-info/top_level.txt
gctools-0.0.3.dist-info/RECORD
